melee_env/__init__.py
melee_env/dconfig.py
melee_env/env.py
melee_env/agents/basic.py
melee_env/agents/util.py
melee_env/install_data/GCPadNew.ini
melee_env/install_data/fast_forward
melee_env-0.30.0.dist-info/LICENSE.txt
melee_env-0.30.0.dist-info/METADATA
melee_env-0.30.0.dist-info/WHEEL
melee_env-0.30.0.dist-info/top_level.txt
melee_env-0.30.0.dist-info/RECORD
