Metadata-Version: 2.1
Name: melee-env
Version: 0.30.0
Summary: A gym-esque environment for Super Smash Bros. Melee.
Home-page: https://github.com/davidtjones/melee-env
Author: David Jones
Author-email: d.t.jones@outlook.com
License: UNKNOWN
Project-URL: Bug Tracker, https://github.com/davidtjones/melee-env/issues
Platform: UNKNOWN
Classifier: Programming Language :: Python :: 3
Classifier: License :: OSI Approved :: GNU Lesser General Public License v3 (LGPLv3)
Classifier: Operating System :: OS Independent
Requires-Python: >=3.6
License-File: LICENSE.txt
Requires-Dist: melee (>=0.30.3)
Requires-Dist: requests (>=2.20)
Requires-Dist: tqdm (>=4.14)
